AUTHORS
CHANGES
LICENSE
MANIFEST.in
README.dialects.rst
README.rst
README.unittests.rst
setup.cfg
setup.py
tox.ini
doc/build/Makefile
doc/build/conf.py
doc/build/contents.rst
doc/build/copyright.rst
doc/build/corrections.py
doc/build/errors.rst
doc/build/glossary.rst
doc/build/index.rst
doc/build/intro.rst
doc/build/requirements.txt
doc/build/sqla_arch_small.png
doc/build/changelog/changelog_01.rst
doc/build/changelog/changelog_02.rst
doc/build/changelog/changelog_03.rst
doc/build/changelog/changelog_04.rst
doc/build/changelog/changelog_05.rst
doc/build/changelog/changelog_06.rst
doc/build/changelog/changelog_07.rst
doc/build/changelog/changelog_08.rst
doc/build/changelog/changelog_09.rst
doc/build/changelog/changelog_10.rst
doc/build/changelog/changelog_11.rst
doc/build/changelog/changelog_12.rst
doc/build/changelog/changelog_13.rst
doc/build/changelog/index.rst
doc/build/changelog/migration_04.rst
doc/build/changelog/migration_05.rst
doc/build/changelog/migration_06.rst
doc/build/changelog/migration_07.rst
doc/build/changelog/migration_08.rst
doc/build/changelog/migration_09.rst
doc/build/changelog/migration_10.rst
doc/build/changelog/migration_11.rst
doc/build/changelog/migration_12.rst
doc/build/changelog/migration_13.rst
doc/build/changelog/unreleased_10/4065.rst
doc/build/changelog/unreleased_10/README.txt
doc/build/changelog/unreleased_11/README.txt
doc/build/changelog/unreleased_12/README.txt
doc/build/changelog/unreleased_13/4618.rst
doc/build/changelog/unreleased_13/4625.rst
doc/build/changelog/unreleased_13/README.txt
doc/build/core/api_basics.rst
doc/build/core/compiler.rst
doc/build/core/connections.rst
doc/build/core/constraints.rst
doc/build/core/custom_types.rst
doc/build/core/ddl.rst
doc/build/core/defaults.rst
doc/build/core/dml.rst
doc/build/core/engines.rst
doc/build/core/engines_connections.rst
doc/build/core/event.rst
doc/build/core/events.rst
doc/build/core/exceptions.rst
doc/build/core/expression_api.rst
doc/build/core/functions.rst
lib/Timi_SQLAlchemy.egg-info/PKG-INFO
lib/Timi_SQLAlchemy.egg-info/SOURCES.txt
lib/Timi_SQLAlchemy.egg-info/dependency_links.txt
lib/Timi_SQLAlchemy.egg-info/requires.txt
lib/Timi_SQLAlchemy.egg-info/top_level.txt
lib/timi_sqlalchemy.egg-info/PKG-INFO
lib/timi_sqlalchemy.egg-info/SOURCES.txt
lib/timi_sqlalchemy.egg-info/dependency_links.txt
lib/timi_sqlalchemy.egg-info/requires.txt
lib/timi_sqlalchemy.egg-info/top_level.txt
