Metadata-Version: 2.1
Name: timi-sqlalchemy
Version: 0.0.1
Summary: Database Abstraction Library
Home-page: http://www.sqlalchemy.org
Author: Timi.long
Author-email: lixiaolong@smuer.cn
License: MIT License
Platform: UNKNOWN
Classifier: Development Status :: 5 - Production/Stable
Classifier: Intended Audience :: Developers
Classifier: License :: OSI Approved :: MIT License
Classifier: Programming Language :: Python
Classifier: Programming Language :: Python :: 2
Classifier: Programming Language :: Python :: 2.7
Classifier: Programming Language :: Python :: 3
Classifier: Programming Language :: Python :: 3.4
Classifier: Programming Language :: Python :: 3.5
Classifier: Programming Language :: Python :: 3.6
Classifier: Programming Language :: Python :: 3.7
Classifier: Programming Language :: Python :: Implementation :: CPython
Classifier: Programming Language :: Python :: Implementation :: PyPy
Classifier: Topic :: Database :: Front-Ends
Classifier: Operating System :: OS Independent
Requires-Python: >=2.7, !=3.0.*, !=3.1.*, !=3.2.*, !=3.3.*
Provides-Extra: postgresql_pg8000
Provides-Extra: postgresql_psycopg2binary
Provides-Extra: mssql_pymssql
Provides-Extra: mssql
Provides-Extra: mysql
Provides-Extra: pymysql
Provides-Extra: postgresql_psycopg2cffi
Provides-Extra: oracle
Provides-Extra: mssql_pyodbc
Provides-Extra: postgresql
